<?xml version="1.0" encoding="utf-8" ?>
<dwsync>
<file name="modules-fieldgroup-panels-content_types.de.po" local="129217082400000000" remote="129217082400000000" testing="0" />
<file name="modules-fieldgroup-panels-content_types.pot" local="129217082400000000" remote="129217082400000000" testing="0" />
<file name="modules-fieldgroup.de.po" local="129217082400000000" remote="129217082400000000" testing="0" />
<file name="modules-fieldgroup.fr.po" local="129217082400000000" remote="129217082400000000" testing="0" />
<file name="modules-fieldgroup.hu.po" local="129217082400000000" remote="129217082400000000" testing="0" />
<file name="modules-fieldgroup.nl.po" local="129217082400000000" remote="129217082400000000" testing="0" />
<file name="modules-fieldgroup.pot" local="129217082400000000" remote="129217082400000000" testing="0" />
<file name="modules-fieldgroup.sv.po" local="129217082400000000" remote="129217082400000000" testing="0" />
</dwsync>