<?xml version="1.0" encoding="utf-8" ?>
<dwsync>
<file name="CHANGELOG.txt" local="129137586000000000" remote="129137586000000000" testing="0" />
<file name="INSTALL.txt" local="129137586600000000" remote="129137586600000000" testing="0" />
<file name="LICENSE.txt" local="129137586600000000" remote="129137586600000000" testing="0" />
<file name="README.txt" local="129137586600000000" remote="129137586600000000" testing="0" />
<file name="date-rtl.css" local="129137586000000000" remote="129137586000000000" testing="0" />
<file name="date.css" local="129137586000000000" remote="129137586000000000" testing="0" />
<file name="date_api.admin.inc" local="129137586000000000" remote="129137586000000000" testing="0" />
<file name="date_api.info" local="129137586000000000" remote="129137586000000000" testing="0" />
<file name="date_api.install" local="129137586000000000" remote="129137586000000000" testing="0" />
<file name="date_api.js" local="129137586000000000" remote="129137586000000000" testing="0" />
<file name="date_api.module" local="129137586000000000" remote="129137586000000000" testing="0" />
<file name="date_api_elements.inc" local="129137586000000000" remote="129137586000000000" testing="0" />
<file name="date_api_formats_list.inc" local="129137586000000000" remote="129137586000000000" testing="0" />
<file name="date_api_ical.inc" local="129137586000000000" remote="129137586000000000" testing="0" />
<file name="date_api_sql.inc" local="129137586000000000" remote="129137586000000000" testing="0" />
</dwsync>